wut/__init__.py
wut/webserver.py
wut-0.0.2.dist-info/LICENSE
wut-0.0.2.dist-info/METADATA
wut-0.0.2.dist-info/WHEEL
wut-0.0.2.dist-info/top_level.txt
wut-0.0.2.dist-info/RECORD
