Metadata-Version: 2.1
Name: wut
Version: 0.0.2
Summary: Python Web Utilities
Home-page: https://ninjamar.github.io/wut
Author: ninjamar
License: UNKNOWN
Platform: UNKNOWN
Requires-Python: >=3.7
License-File: LICENSE
